pltgui/__init__.py
pltgui/_i_btn_.py
pltgui-0.32.dist-info/LICENSE
pltgui-0.32.dist-info/METADATA
pltgui-0.32.dist-info/WHEEL
pltgui-0.32.dist-info/top_level.txt
pltgui-0.32.dist-info/RECORD
