Metadata-Version: 2.1
Name: pltgui
Version: 0.32
Summary: A GUI with matplotlib, can use on all OS.
Home-page: https://gitee.com/drjiezheng/pltgui
Author: Dr Jie Zheng
Author-email: jiezheng@nao.cas.cn
License: MIT
Classifier: Development Status :: 5 - Production/Stable
Classifier: Intended Audience :: Science/Research
Classifier: License :: OSI Approved :: MIT License
Classifier: Operating System :: OS Independent
Classifier: Programming Language :: Python :: 3.7
Classifier: Topic :: Scientific/Engineering :: Physics
Classifier: Topic :: Scientific/Engineering :: Astronomy
Requires: numpy
Requires: matplotlib
License-File: LICENSE
